README.txt
setup.py
ckanext/__init__.py
ckanext/dgu/__init__.py
ckanext/dgu/curation.py
ckanext/dgu/schema.py
ckanext/dgu/bis/__init__.py
ckanext/dgu/bis/bis.py
ckanext/dgu/bis/tests/__init__.py
ckanext/dgu/cospread/__init__.py
ckanext/dgu/cospread/cospread.py
ckanext/dgu/cospread/loader.py
ckanext/dgu/forms/__init__.py
ckanext/dgu/forms/package_gov3.py
ckanext/dgu/ons/__init__.py
ckanext/dgu/ons/downloader.py
ckanext/dgu/ons/importer.py
ckanext/dgu/ons/loader.py
ckanext/dgu/scripts/__init__.py
ckanext/dgu/scripts/change_licenses.py
ckanext/dgu/scripts/change_licenses_cmd.py
ckanext/dgu/scripts/common.py
ckanext/dgu/scripts/mass_changer.py
ckanext/dgu/scripts/mass_changer_cmd.py
ckanext/dgu/scripts/ofsted_fix.py
ckanext/dgu/scripts/ofsted_fix_cmd.py
ckanext/dgu/scripts/ons_analysis.py
ckanext/dgu/scripts/ons_analysis_cmd.py
ckanext/dgu/scripts/transfer_url.py
ckanext/dgu/scripts/transfer_url_cmd.py
ckanext/dgu/tests/__init__.py
ckanext/dgu/tests/test_schema.py
ckanext/dgu/tests/bis/__init__.py
ckanext/dgu/tests/bis/test_bis.py
ckanext/dgu/tests/cospread/__init__.py
ckanext/dgu/tests/cospread/test_cospread.py
ckanext/dgu/tests/forms/__init__.py
ckanext/dgu/tests/forms/test_package_gov3.py
ckanext/dgu/tests/functional/__init__.py
ckanext/dgu/tests/functional/test_package_gov3.py
ckanext/dgu/tests/ons/__init__.py
ckanext/dgu/tests/ons/ons_data_tester.py
ckanext/dgu/tests/ons/test_ons_download.py
ckanext/dgu/tests/ons/test_ons_importer.py
ckanext/dgu/tests/ons/test_ons_loader.py
ckanext/dgu/tests/scripts/__init__.py
ckanext/dgu/tests/scripts/test_change_licenses.py
ckanext/dgu/tests/scripts/test_mass_changer.py
ckanext_dgu.egg-info/PKG-INFO
ckanext_dgu.egg-info/SOURCES.txt
ckanext_dgu.egg-info/dependency_links.txt
ckanext_dgu.egg-info/entry_points.txt
ckanext_dgu.egg-info/requires.txt
ckanext_dgu.egg-info/top_level.txt