Metadata-Version: 1.0
Name: ckanext-dgu
Version: 0.3
Summary: CKAN DGU extensions
Home-page: http://knowledgeforge.net/ckan/
Author: Open Knowledge Foundation
Author-email: info@okfn.org
License: AGPL
Keywords: data packaging component tool server
Platform: UNKNOWN
